MANIFEST.in
README.md
setup.py
test_randomcolor.py
randomcolor/__init__.py
randomcolor.egg-info/PKG-INFO
randomcolor.egg-info/SOURCES.txt
randomcolor.egg-info/dependency_links.txt
randomcolor.egg-info/top_level.txt
randomcolor/lib/colormap.json