Metadata-Version: 1.0
Name: randomcolor
Version: 0.4.4.3
Summary: For generating attractive random colors
Home-page: https://github.com/kevinwuhoo/randomcolor-py
Author: Kevin Wu
Author-email: me@kevinformatics.com
License: UNKNOWN
Keywords: python random color generator
Platform: UNKNOWN
